{
  "type": "S3",
  "managed": true,
  "featureGroup": false,
  "formatType": "csv",
  "checklists": {
    "checklists": []
  },
  "checks": [],
  "customMeta": {
    "kv": {}
  },
  "flowOptions": {
    "virtualizable": true,
    "rebuildBehavior": "NORMAL",
    "crossProjectBuildBehavior": "DEFAULT"
  },
  "readWriteOptions": {
    "preserveOrder": false,
    "writeBuckets": 1,
    "forceSingleOutputFile": false,
    "defaultReadOrdering": {
      "enabled": false,
      "rules": []
    }
  },
  "formatParams": {
    "style": "unix",
    "charset": "utf8",
    "separator": "\t",
    "quoteChar": "\"",
    "escapeChar": "\\",
    "dateSerializationFormat": "ISO",
    "arrayMapFormat": "json",
    "hiveSeparators": [
      "\u0002",
      "\u0003",
      "\u0004",
      "\u0005",
      "\u0006",
      "\u0007",
      "\b"
    ],
    "skipRowsBeforeHeader": 0,
    "parseHeaderRow": false,
    "skipRowsAfterHeader": 0,
    "probableNumberOfRecords": 0,
    "normalizeBooleans": false,
    "normalizeDoubles": true,
    "readAdditionalColumnsBehavior": "INSERT_IN_DATA_WARNING",
    "readMissingColumnsBehavior": "DISCARD_SILENT",
    "readDataTypeMismatchBehavior": "DISCARD_WARNING",
    "writeDataTypeMismatchBehavior": "DISCARD_WARNING",
    "fileReadFailureBehavior": "FAIL",
    "compress": "gz"
  },
  "partitioning": {
    "ignoreNonMatchingFile": false,
    "considerMissingRequestedPartitionsAsEmpty": false,
    "dimensions": []
  },
  "versionTag": {
    "versionNumber": 1,
    "lastModifiedBy": {
      "login": "rinnijoshi.16@gmail.com"
    },
    "lastModifiedOn": 1686860188291,
    "extendedProperties": {}
  },
  "creationTag": {
    "versionNumber": 0,
    "lastModifiedBy": {
      "login": "rinnijoshi.16@gmail.com"
    },
    "lastModifiedOn": 1686859904807,
    "extendedProperties": {}
  },
  "tags": [],
  "params": {
    "bucket": "gis-data-ca-central-1",
    "metastoreSynchronizationEnabled": true,
    "metastoreDatabaseName": "default",
    "metastoreTableName": "${projectKey}_netflix_titles_cast_counting",
    "connection": "dataiku-managed-storage",
    "path": "/managed-dss-data/${projectKey}/netflix_titles_cast_counting",
    "notReadyIfEmpty": false,
    "filesSelectionRules": {
      "mode": "ALL",
      "excludeRules": [],
      "includeRules": [],
      "explicitFiles": []
    }
  },
  "schema": {
    "columns": [
      {"name":"show_id","type":"string"},
      {"name":"type","type":"string"},
      {"name":"title","type":"string"},
      {"name":"director","type":"string"},
      {"name":"cast","type":"string"},
      {"name":"country","type":"string"},
      {"name":"date_added","type":"string"},
      {"name":"release_year","type":"bigint"},
      {"name":"rating","type":"string"},
      {"name":"duration","type":"string"},
      {"name":"listed_in","type":"string"},
      {"name":"description","type":"string"},
      {"name":"count","type":"bigint"}
    ],
    "userModified": true
  },
  "dkuProperties": [],
  "metrics": {
    "probes": [
      {
        "type": "basic",
        "enabled": true,
        "computeOnBuildMode": "PARTITION",
        "meta": {
          "name": "Basic data",
          "level": 0
        },
        "configuration": {}
      },
      {
        "type": "records",
        "enabled": true,
        "computeOnBuildMode": "NO",
        "meta": {
          "name": "Record count",
          "level": 0
        },
        "configuration": {}
      }
    ],
    "engineConfig": {
      "padRunsWithMetrics": false,
      "hive": {
        "active": true,
        "extraConf": []
      },
      "basic": {},
      "dss": {
        "active": true,
        "selection": {
          "useMemTable": false,
          "filter": {
            "distinct": false,
            "enabled": false
          },
          "partitionSelectionMethod": "ALL",
          "latestPartitionsN": 1,
          "ordering": {
            "enabled": false,
            "rules": []
          },
          "samplingMethod": "FULL",
          "maxRecords": -1,
          "targetRatio": 0.02,
          "withinFirstN": -1,
          "maxReadUncompressedBytes": -1
        }
      },
      "sql": {
        "active": true
      },
      "impala": {
        "active": true
      },
      "spark": {
        "active": true,
        "extraConf": []
      },
      "python": {}
    },
    "displayedState": {
      "columns": [],
      "metrics": [
        "basic:COUNT_COLUMNS",
        "basic:COUNT_FILES",
        "basic:SIZE",
        "records:COUNT_RECORDS"
      ]
    }
  },
  "metricsChecks": {
    "runOnBuild": false,
    "checks": [],
    "displayedState": {
      "checks": []
    }
  },
  "customFields": {}
}